{"unidade": "Escola de Engenharia de S\u00e3o Carlos", "departamento": "Disciplinas Interdepartamentais da EESC", "campus": "S\u00e3o Carlos", "codigo": "1800300", "nome": "Laborat\u00f3rio de Projeto, Materiais e Manufatura", "creditos_aula": 6, "creditos_trabalho": 0, "objetivos": "Desenvolver as habilidades na especifica\u00e7\u00e3o do produto, na aplica\u00e7\u00e3o do projeto e materiais, no processamento, na integra\u00e7\u00e3o e testes dos componentes. O processo de aprendizagem dos alunos na disciplina busca desenvolver um conjunto de Compet\u00eancias (C) espec\u00edficas, a partir de\nHabilidades (H), conforme destacado a seguir:\nC1: Organizar o processo de desenvolvimento de materiais desde a concep\u00e7\u00e3o, planejamento e organiza\u00e7\u00e3o de todas as etapas necess\u00e1rias para a sua produ\u00e7\u00e3o, projeto de produtos, modifica\u00e7\u00e3o e outras atividades correlatas;\nC2: Habilidade para trabalho em equipe e de organiza\u00e7\u00e3o para a realiza\u00e7\u00e3o de um projeto com complexidade consider\u00e1vel empregando as ferramentas que aprendeu no curso at\u00e9 a data presente de realiza\u00e7\u00e3o da disciplina;\nC3: Habilidade de propor e convencer outras pessoas uma estrat\u00e9gia e conceito empregando para isso o seu conhecimento sobre materiais, planejamento e manufatura.", "programa_resumido": "Desenvolver um projeto relacionado com a manufatura de um material ou um produto previamente negociado com os professores, utilizando o laborat\u00f3rio de forma integrada e aplicando conhecimentos obtidos durante o curso.", "turmas": [{"codigo": "2025101", "inicio": "24/02/2025", "fim": "07/07/2025", "tipo": "Pr\u00e1tica", "observacoes": "Curso: Engenharia de Materiais e Manufatura\n\nSala:", "horario": [{"dia": "qui", "inicio": "13:20", "fim": "19:00", "professores": ["(R) Antonio Jos\u00e9 Felix de Carvalho"]}], "vagas": {"Obrigat\u00f3ria": {"vagas": 50, "inscritos": 24, "pendentes": 0, "matriculados": 24, "grupos": {}}}}]}