{"unidade": "Faculdade de Filosofia, Ci\u00eancias e Letras de Ribeir\u00e3o Preto", "departamento": "Psicologia", "campus": "Ribeir\u00e3o Preto", "codigo": "5940628", "nome": "Psicologia Social I", "creditos_aula": 2, "creditos_trabalho": 1, "objetivos": "Geral: \nInformar o aluno a respeito da Hist\u00f3ria da Psicologia Social e de algumas das principais teorias da Psicologia Social, com vistas a situar os problemas e conceitos dentro de uma perspectiva epistemol\u00f3gica e hist\u00f3rica. \n\nEspec\u00edficos:\n- Introduzir numa perspectiva hist\u00f3rica os principais modelos te\u00f3ricos em Psicologia Social\n- Estimular a an\u00e1lise de problemas psicossociais por diversas perspectivas te\u00f3ricas.\n- Desenvolver o racioc\u00ednio cr\u00edtico e a autonomia intelectual no campo da Psicologia Social.", "programa_resumido": "Introduzir o aluno no conhecimento da Hist\u00f3ria da Psicologia Social e de suas grandes teorias, com vistas a analisar criticamente os graves problemas sociais e vislumbrar as v\u00e1rias estrat\u00e9gias e t\u00e9cnicas de investiga\u00e7\u00e3o e interven\u00e7\u00e3o. Apresentar ao aluno os campos de pesquisa e de atua\u00e7\u00e3o pr\u00e1tica nos n\u00edveis psicossocial, sociodin\u00e2mico e comunit\u00e1rio.", "turmas": [{"codigo": "2025101", "inicio": "24/02/2025", "fim": "07/07/2025", "tipo": "Te\u00f3rica", "observacoes": "Sala 204 do Centro Did\u00e1tico - Bloco 16", "horario": [{"dia": "qua", "inicio": "10:00", "fim": "12:00", "professores": ["(R) Jose Francisco Miguel Henriques Bairrao"]}], "vagas": {"Obrigat\u00f3ria": {"vagas": 45, "inscritos": 27, "pendentes": 0, "matriculados": 0, "grupos": {}}}}]}