{"unidade": "Faculdade de Filosofia, Ci\u00eancias e Letras de Ribeir\u00e3o Preto", "departamento": "Educa\u00e7\u00e3o, Informa\u00e7\u00e3o e Comunica\u00e7\u00e3o", "campus": "Ribeir\u00e3o Preto", "codigo": "5962118", "nome": "Introdu\u00e7\u00e3o \u00e0s Tecnologias da Informa\u00e7\u00e3o e Comunica\u00e7\u00e3o", "creditos_aula": 4, "creditos_trabalho": 1, "objetivos": "A disciplina objetiva apresentar recursos das Tecnologias da Informa\u00e7\u00e3o e Comunica\u00e7\u00e3o aplicados a Biblioteconomia e Ci\u00eancia da Informa\u00e7\u00e3o, por meio de seus aspectos te\u00f3ricos e pr\u00e1ticos b\u00e1sicos, permitindo ao aluno uma an\u00e1lise cr\u00edtica sobre os recursos computacionais aplicados ao tratamento da informa\u00e7\u00e3o.", "programa_resumido": "Conceitos e pr\u00e1ticas introdut\u00f3rias acerca de Tecnologias da Informa\u00e7\u00e3o e da Comunica\u00e7\u00e3o ligadas a Biblioteconomia e Ci\u00eancias da Informa\u00e7\u00e3o.", "turmas": [{"codigo": "2025104", "inicio": "24/02/2025", "fim": "07/07/2025", "tipo": "Te\u00f3rica", "observacoes": "Sala 107 do Centro Did\u00e1tico - Bloco 16.", "horario": [{"dia": "qui", "inicio": "19:00", "fim": "20:40", "professores": ["(R) Jose Eduardo Santarem Segundo"]}, {"dia": "qui", "inicio": "20:50", "fim": "22:30", "professores": ["(R) Jose Eduardo Santarem Segundo"]}], "vagas": {"Obrigat\u00f3ria": {"vagas": 45, "inscritos": 1, "pendentes": 0, "matriculados": 0, "grupos": {}}, "Optativa Livre": {"vagas": 5, "inscritos": 0, "pendentes": 0, "matriculados": 0, "grupos": {"FFCLRP - todos exceto BCI": {"vagas": 5, "inscritos": 0, "pendentes": 0, "matriculados": 0}, "Qualquer Unidade da USP": {"vagas": 0, "inscritos": 0, "pendentes": 0, "matriculados": 0}}}}}]}