{"unidade": "Instituto de Ci\u00eancias Biom\u00e9dicas", "departamento": "Microbiologia", "campus": "Outro", "codigo": "BMM0560", "nome": "Microbiologia Oral", "creditos_aula": 5, "creditos_trabalho": 0, "objetivos": "O aluno dever\u00e1 conhecer a microbiota oral e patog\u00eanica da cavidade oral; compreender o papel desempenhado pelos microrganismos orais na sa\u00fade e diferentes doen\u00e7as da cavidade bucal e de s\u00edtios extra-orais; compreender a etiologia das doen\u00e7as infecciosas orais; aplicar esses conhecimentos para a preven\u00e7\u00e3o e tratamento das doen\u00e7as infecciosas orais e extra-orais.", "programa_resumido": "Te\u00f3rico:- V\u00edrus de interesse em Odontologia. Fungos de interesse em Odontologia. M\u00e9todos de estudo da microbiota oral. diversidade microbiana na cavidade oral. ecologia oral: intera\u00e7\u00f5es microbianas e rela\u00e7\u00e3o com o hospedeiro. Biofilmes orais, forma\u00e7\u00e3o, estrutura e potencial patog\u00eanico. Microbiota associada a carie dental. Risco de c\u00e1rie. Microbiota associada \u00e0s doen\u00e7as peridentais. Microbiota associada \u00e0s infec\u00e7\u00f5es pulpares e periapicais. Transmissibilidade de bact\u00e9rias cariog\u00eanicas e periodonto patog\u00eanicas. Associa\u00e7\u00e3o entre doen\u00e7as sist\u00eamicas e infec\u00e7\u00f5es orais. Antibi\u00f3ticos e antiss\u00e9pticos no controle de infec\u00e7\u00f5es orais. Controle de microrganismos para preven\u00e7\u00e3o e tratamento das doen\u00e7as associadas ao biofilme dental.\n\nPr\u00e1tico:\n- Biofilmes: pat\u00f3genos periodontais. M\u00e9todos bacteriol\u00f3gicos de avalia\u00e7\u00e3o de risco de c\u00e1rie. Efeito de antiss\u00e9pticos sobre a microbiota oral.", "turmas": []}