{"unidade": "Faculdade de Ci\u00eancias Farmac\u00eauticas de Ribeir\u00e3o Preto", "departamento": "Disciplinas Interdepartamentais da FCFRP", "campus": "Ribeir\u00e3o Preto", "codigo": "CGF2085", "nome": "T\u00f3picos de Psicologia Aplicada \u00e0 Farm\u00e1cia", "creditos_aula": 1, "creditos_trabalho": 0, "objetivos": "Conhecer os conceitos b\u00e1sicos da psicologia social e da sa\u00fade; \nCompreender os aspectos psicol\u00f3gicos subjacentes aos processos de sa\u00fade e doen\u00e7a;\nRefletir sobre os fundamentos da psicologia que se articulam com a profiss\u00e3o farmac\u00eautica.", "programa_resumido": "A qu\u00edmica das emo\u00e7\u00f5es. A rela\u00e7\u00e3o terap\u00eautica entre o profissional farmac\u00eautico, o paciente e a fam\u00edlia. Ciclo Vital: Aspectos psicol\u00f3gicos da gravidez, parto e puerp\u00e9rio. Coach e Carreira. Depress\u00e3o e ansiedade. Desenvolvimento infantil e adolescente. Diagn\u00f3stico psicol\u00f3gico, progn\u00f3stico e plano de tratamento. Dist\u00farbios de conduta e aprendizagem. Drogas e psico-farmacologia. Emo\u00e7\u00f5es e psicopatologia. Equipes multidisciplinares. Experi\u00eancias de um farmac\u00eautico no cuidado, equipe multiprofissional e mercado de trabalho. Identidade. Mem\u00f3ria, cogni\u00e7\u00e3o e afetividade. O objeto de estudo da psicologia e suas intersec\u00e7\u00f5es com a atividade profissional do farmac\u00eautico. Oncologia Pedi\u00e1trica, cuidados paliativos, hospital - possibilidades de compreens\u00e3o e atua\u00e7\u00e3o. Orat\u00f3ria: A import\u00e2ncia de saber falar em p\u00fablico. Origem e hist\u00f3ria da psicologia social e cl\u00ednica. Perfil profissional esperado pelas empresas farmac\u00eauticas. Psicopatologia. Rela\u00e7\u00f5es \u00e9tnico-raciais na universidade. Sa\u00fade mental e psicopatologia. Sexualidade. Transtorno de d\u00e9ficit de aten\u00e7\u00e3o e hiperatividade. Vida adulta, maturidade e envelhecimento.", "turmas": [{"codigo": "20242DT", "inicio": "05/08/2024", "fim": "12/12/2024", "tipo": "Te\u00f3rica", "observacoes": "Aulas - Anfiteatro 1", "horario": [{"dia": "ter", "inicio": "08:00", "fim": "10:00", "professores": [""]}], "vagas": {"Obrigat\u00f3ria": {"vagas": 0, "inscritos": 0, "pendentes": 0, "matriculados": 0, "grupos": {}}, "Optativa Eletiva": {"vagas": 88, "inscritos": 41, "pendentes": 0, "matriculados": 0, "grupos": {"FCFRP - Para toda a unidade para os cursos 60013, 60014 e 60015": {"vagas": 88, "inscritos": 41, "pendentes": 0, "matriculados": 0}}}}}]}