{"unidade": "Faculdade de Educa\u00e7\u00e3o", "departamento": "Metodologia do Ensino e Ed Comparada", "campus": "S\u00e3o Paulo", "codigo": "EDM0612", "nome": "Crian\u00e7a, inf\u00e2ncia e diferen\u00e7as", "creditos_aula": 4, "creditos_trabalho": 0, "objetivos": "Fornecer aos estudantes de Pedagogia e das Ci\u00eancias Humanas os elementos te\u00f3ricos e anal\u00edticos para que\ncompreendam a emerg\u00eancia da crian\u00e7a no cen\u00e1rio cient\u00edfico ocidental, bem como, o conceito de inf\u00e2ncia.\nAnalisar as crian\u00e7as e as inf\u00e2ncias na transversalidade dos temas relativos \u00e0s diferen\u00e7as: rela\u00e7\u00f5es \u00e9tnico-\nraciais, g\u00eanero e sexualidade e outras sob a perspectiva dos grupos subalternos e/ou minorit\u00e1rios.", "programa_resumido": "O programa da disciplina visa a assegurar aos estudantes o conhecimento sobre as principais epistemologias e metodologias para a compreens\u00e3o da crian\u00e7a e inf\u00e2ncia. A diferen\u00e7a ser\u00e1 compreendida a partir dos fil\u00f3sofos da diferen\u00e7a e dos autores p\u00f3s-coloniais que analisam ra\u00e7a, rela\u00e7\u00f5es \u00e9tnico-racial, sexualidade e g\u00eanero.", "turmas": [{"codigo": "2024203", "inicio": "05/08/2024", "fim": "11/12/2024", "tipo": "Te\u00f3rica", "horario": [{"dia": "seg", "inicio": "19:30", "fim": "23:00", "professores": ["(R) Anete Abramowicz"]}], "vagas": {"Obrigat\u00f3ria": {"vagas": 0, "inscritos": 0, "pendentes": 0, "matriculados": 0, "grupos": {}}, "Optativa Eletiva": {"vagas": 60, "inscritos": 36, "pendentes": 0, "matriculados": 0, "grupos": {"FE -  para toda a Unidade": {"vagas": 60, "inscritos": 36, "pendentes": 0, "matriculados": 0}}}}}]}