{"unidade": "Faculdade de Filosofia, Letras e Ci\u00eancias Humanas", "departamento": "Letras Modernas", "campus": "Outro", "codigo": "FLM0685", "nome": "Literatura Alem\u00e3: Bertolt Brecht", "creditos_aula": 2, "creditos_trabalho": 0, "objetivos": "Introdu\u00e7\u00e3o \u00e0 obra de Bertolt Brecht, abordando-se, al\u00e9m da produ\u00e7\u00e3o teatral, as obras narrativa, l\u00edrica e cr\u00edtico-te\u00f3rica.", "programa_resumido": "O curso tratar\u00e1 de alguns dos aspectos centrais da obra de Bertolt Brecht, abordando os seguintes t\u00f3picos: a) contextualiza\u00e7\u00e3o hist\u00f3rica; b) di\u00e1logo e confronto com autores contempor\u00e2neos; c) a quest\u00e3o do realismo (debate sobre o Expressionismo: L\u00fak\u00e1cs e Bloch); d) a situa\u00e7\u00e3o de Brecht no Brasil; e) o teatro \u00e9pico: origem e desdobramentos.", "turmas": []}