{"unidade": "Escola Superior de Agricultura \"Luiz de Queiroz\"", "departamento": "Ci\u00eancias Exatas", "campus": "Outro", "codigo": "LCE0602", "nome": "Estat\u00edstica Experimental", "creditos_aula": 4, "creditos_trabalho": 0, "objetivos": "A disciplina Estat\u00edstica Experimental tem como objetivo principal estimular o senso cr\u00edtico do estudante com rela\u00e7\u00e3o \u00e0 experimenta\u00e7\u00e3o, de tal modo que, recebendo informa\u00e7\u00f5es a respeito da pesquisa, o estudante seja capaz de planejar e conduzir um experimento, analisar os dados e interpretar os resultados.", "programa_resumido": "1. Planejamento de experimentos. 2. Planejamento, an\u00e1lise e interpreta\u00e7\u00e3o de resultados de experimentos inteiramente casualizados, em blocos casualizados, em quadrados latinos, fatoriais, em parcelas subdivididas e em faixas. 3. Compara\u00e7\u00f5es m\u00faltiplas (T\u00e9cnica de compara\u00e7\u00f5es entre m\u00e9dias). 4. An\u00e1lise de regress\u00e3o polinomial. 5. Exig\u00eancias do modelo matem\u00e1tico - Transforma\u00e7\u00e3o de dados. 6. Confundimento nos ensaios fatoriais. 7. An\u00e1lise de grupos de experimentos.", "turmas": []}