{"unidade": "Escola Polit\u00e9cnica", "departamento": "Engenharia de Energia e Automa\u00e7\u00e3o El\u00e9tricas", "campus": "S\u00e3o Paulo", "codigo": "PEA3406", "nome": "Laborat\u00f3rio de Sistemas  de Pot\u00eancia", "creditos_aula": 2, "creditos_trabalho": 0, "objetivos": "An\u00e1lise de sistemas el\u00e9tricos de pot\u00eancia por meio de modelos em escala reduzida e simula\u00e7\u00f5es computacionais, complementando a teoria ministrada nas disciplinas: Sistemas de Pot\u00eancia I e II.", "programa_resumido": "1. Harm\u00f4nicas em transformadores trif\u00e1sicos. 2. Mini sistema de pot\u00eancia: simula\u00e7\u00e3o utilizando um sistema em escala reduzida, composto por gerador, linha de transmiss\u00e3o, carga e reatores est\u00e1ticos em deriva\u00e7\u00e3o. 3. Diagrama sequencial de transformadores: descri\u00e7\u00e3o do diagrama de sequ\u00eancia zero para os diversos tipos de liga\u00e7\u00e3o de um banco de transformadores monof\u00e1sico. 4. Curto-circuito em transformadores trif\u00e1sicos: an\u00e1lise dos diversos tipos de curtos-circuitos em transformadores trif\u00e1sicos, fazendo uso da teoria de componentes sim\u00e9tricas e diagrama de sequencias. 5. Curto-circuito em sistemas de pot\u00eancia: modelagem de sistemas de pot\u00eancia e simula\u00e7\u00e3o de curto-circuito fazendo uso de ferramentas computacionais. 6. Fluxo de pot\u00eancia: utiliza\u00e7\u00e3o de recursos computacionais para o c\u00e1lculo do fluxo de pot\u00eancia de sistemas de energia el\u00e9trica por meio dos principais m\u00e9todos (Gauss, Gauss-Saidel e Newton-Raphson) .", "turmas": [{"codigo": "2024201", "inicio": "05/08/2024", "fim": "12/12/2024", "tipo": "Pr\u00e1tica", "horario": [{"dia": "seg", "inicio": "07:30", "fim": "11:00", "professores": ["Carlos Frederico Meschini Almeida"]}], "vagas": {"Obrigat\u00f3ria": {"vagas": 16, "inscritos": 6, "pendentes": 0, "matriculados": 0, "grupos": {}}, "Extracurricular": {"vagas": 2, "inscritos": 0, "pendentes": 0, "matriculados": 0, "grupos": {}}}}, {"codigo": "2024202", "inicio": "05/08/2024", "fim": "12/12/2024", "tipo": "Pr\u00e1tica", "horario": [{"dia": "seg", "inicio": "07:30", "fim": "11:00", "professores": ["Carlos Frederico Meschini Almeida"]}], "vagas": {"Obrigat\u00f3ria": {"vagas": 15, "inscritos": 16, "pendentes": 0, "matriculados": 0, "grupos": {}}, "Extracurricular": {"vagas": 3, "inscritos": 0, "pendentes": 0, "matriculados": 0, "grupos": {}}}}]}