{"unidade": "Escola Polit\u00e9cnica", "departamento": "Engenharia Mec\u00e2nica", "campus": "Outro", "codigo": "PME3360", "nome": "Transfer\u00eancia de Calor", "creditos_aula": 4, "creditos_trabalho": 0, "objetivos": "-Capacitar o aluno a analisar e projetar processos de transfer\u00eancia de calor.", "programa_resumido": "Introdu\u00e7\u00e3o aos mecanismos de transfer\u00eancia de calor. Condu\u00e7\u00e3o unidimensional em regime permanente. Condu\u00e7\u00e3o em regime transit\u00f3rio. Equa\u00e7\u00f5es da transfer\u00eancia de calor por convec\u00e7\u00e3o. Transfer\u00eancia de calor no escoamento for\u00e7ado externo e interno. Radia\u00e7\u00e3o t\u00e9rmica. Transfer\u00eancia de calor por radia\u00e7\u00e3o entre superf\u00edcies.", "turmas": []}