{"unidade": "Faculdade de Medicina de Ribeir\u00e3o Preto", "departamento": "Disciplinas Interdepartamentais", "campus": "Outro", "codigo": "RCG5009", "nome": "Trabalho de Conclus\u00e3o de Curso I", "creditos_aula": 1, "creditos_trabalho": 4, "objetivos": "Introduzir o aluno na linguagem cient\u00edfica atrav\u00e9s de uma vis\u00e3o geral da experimenta\u00e7\u00e3o e das v\u00e1rias formas de planejamento de pesquisa, tendo como objetivo terminal, instrumentalizar o aluno para elaborar projetos de pesquisa. Orientar o aluno para o desenvolvimento de um projeto referente ao Trabalho de Conclus\u00e3o do Curso", "programa_resumido": "Participa\u00e7\u00e3o em atividades estipuladas pelo orientador como semin\u00e1rios, elabora\u00e7\u00e3o de relat\u00f3rios ou textos anal\u00edticos sobre assuntos relativos a tem\u00e1tica do projeto desenvolvido, atividades laboratoriais ou cl\u00ednicas, entre outras.", "turmas": []}