{"unidade": "Faculdade de Medicina de Ribeir\u00e3o Preto", "departamento": "Disciplinas Interdepartamentais de Fonoaudiologia da FMRP", "campus": "Ribeir\u00e3o Preto", "codigo": "RFO3004", "nome": "Fundamentos de Lingu\u00edstica", "creditos_aula": 2, "creditos_trabalho": 0, "objetivos": "A disciplina visa proporcionar ao aluno o conhecimento e reflex\u00e3o sobre alguns conceitos b\u00e1sicos da teoria lingu\u00edstica os pressupostos e m\u00e9todos da Lingu\u00edstica relacionando-os a teoria e pr\u00e1tica da Fonoaudiologia.", "programa_resumido": "Introdu\u00e7\u00e3o \u00e0 ci\u00eancia Lingu\u00edstica. Conceito de Comunica\u00e7\u00e3o. Linguagem. L\u00edngua. Fala.  Princ\u00edpios b\u00e1sicos do Estruturalismo, da Lingu\u00edstica Hist\u00f3rica, de Sociolinguistica, Neruolingu\u00edstica e Psicolinguistica aplicados a Fonoaudiologia.", "turmas": [{"codigo": "20251T1", "inicio": "12/03/2025", "fim": "25/06/2025", "tipo": "Te\u00f3rica", "horario": [{"dia": "qua", "inicio": "10:00", "fim": "12:00", "professores": ["(R) Patricia Pupin Mandra"]}], "vagas": {"Obrigat\u00f3ria": {"vagas": 35, "inscritos": 0, "pendentes": 0, "matriculados": 0, "grupos": {"FMRP - Fonoaudiologia": {"vagas": 35, "inscritos": 0, "pendentes": 0, "matriculados": 0}}}}}]}