{"unidade": "Escola de Engenharia de S\u00e3o Carlos", "departamento": "Engenharia El\u00e9trica e de Computa\u00e7\u00e3o", "campus": "S\u00e3o Carlos", "codigo": "SEL0378", "nome": "Redes de Computadores", "creditos_aula": 2, "creditos_trabalho": 0, "objetivos": "Introduzir aos alunos de engenharia el\u00e9trica, os conceitos de redes de computadores.", "programa_resumido": "Topologias e Tecnologias de Redes; Equipamentos de Redes; Redes Ethernet; Transmiss\u00e3o e Codifica\u00e7\u00e3o de Dados: Meios F\u00edsicos; Aspectos de Conex\u00e3o Inter-redes; Cabeamento Estruturado; Protocolos Usando Modelo ISO/OSI (N\u00edvel F\u00edsico, Enlace, Rede, Transporte, Sess\u00e3o, Apresenta\u00e7\u00e3o e Aplica\u00e7\u00e3o); Protocolos TCP/IP; M\u00e9todos de Dettec\u00e7\u00e3o de Erros; Aspectos de Seguran\u00e7a de Redes; Aplica\u00e7\u00f5es de Redes de Computadores em Engenharia El\u00e9trica.", "turmas": [{"codigo": "2024201", "inicio": "05/08/2024", "fim": "12/12/2024", "tipo": "Te\u00f3rica", "horario": [{"dia": "ter", "inicio": "14:20", "fim": "16:00", "professores": ["(R) Ivan Nunes da Silva"]}], "vagas": {"Obrigat\u00f3ria": {"vagas": 0, "inscritos": 0, "pendentes": 0, "matriculados": 0, "grupos": {}}, "Optativa Eletiva": {"vagas": 50, "inscritos": 61, "pendentes": 0, "matriculados": 0, "grupos": {}}}}]}