{"unidade": "Escola de Engenharia de S\u00e3o Carlos", "departamento": "Engenharia Mec\u00e2nica", "campus": "S\u00e3o Carlos", "codigo": "SEM0250", "nome": "Sistemas T\u00e9rmicos de Pot\u00eancia", "creditos_aula": 4, "creditos_trabalho": 0, "objetivos": "A disciplina pretende desenvolver no aluno compet\u00eancia para aplicar os conhecimentos de termodin\u00e2mica, mec\u00e2nica dos fluidos e transfer\u00eancia de calor na solu\u00e7\u00e3o de problemas de engenharia na \u00e1rea de motores a combust\u00e3o interna, gera\u00e7\u00e3o e utiliza\u00e7\u00e3o de vapor, turbinas a vapor e a g\u00e1s. No \u00e2mbito mais espec\u00edfico os alunos desenvolver\u00e3o compet\u00eancia para analisar, instalar e operar sistemas t\u00e9rmicos de pot\u00eancia.", "programa_resumido": "Introdu\u00e7\u00e3o aos motores de combust\u00e3o interna. Combust\u00edveis para motores. Prepara\u00e7\u00e3o da mistura combust\u00edvel/ar. Sistemas de alimenta\u00e7\u00e3o dos combust\u00edveis. Sistemas de Igni\u00e7\u00e3o. Ensaios dinamom\u00e9tricos e a performance dos motores. An\u00e1lise de emiss\u00f5es. \u00d3rg\u00e3os principais das turbinas a g\u00e1s. Aplica\u00e7\u00f5es das turbo m\u00e1quinas. Sistemas termoel\u00e9tricos de convers\u00e3o de energia. Visitas t\u00e9cnicas \u00e0 sistemas t\u00e9rmicos de pot\u00eancia.", "turmas": []}