{"unidade": "Escola de Engenharia de S\u00e3o Carlos", "departamento": "Engenharia de Estruturas", "campus": "S\u00e3o Carlos", "codigo": "SET0197", "nome": "Sistemas Estruturais em A\u00e7o e Madeira", "creditos_aula": 4, "creditos_trabalho": 1, "objetivos": "Fornecer aos alunos do curso de Arquitetura e os principais t\u00f3picos necess\u00e1rios ao desenvolvimento de projetos envolvendo elementos estruturais em a\u00e7o e em madeira.", "programa_resumido": "Anatomia da madeira. Propriedades f\u00edsicas e mec\u00e2nicas da madeira. Produtos industrializados de madeira. Dispositivos de liga\u00e7\u00e3o em madeira e suas aplica\u00e7\u00f5es. Sistemas estruturais e construtivos em madeira. Durabilidade da madeira. Obten\u00e7\u00e3o do a\u00e7o e seus produtos comerciais. No\u00e7\u00f5es b\u00e1sicas sobre o dimensionamento de elementos estruturais em a\u00e7o: tra\u00e7\u00e3o, compress\u00e3o e flex\u00e3o. Dispositivos de liga\u00e7\u00e3o e suas aplica\u00e7\u00f5es: soldas e parafusos. Sistemas estruturais e construtivos em a\u00e7o.", "turmas": [{"codigo": "2024201", "inicio": "05/08/2024", "fim": "12/12/2024", "tipo": "Te\u00f3rica", "observacoes": "Cursos: Arquitetura e Urbanismo e Engenharia Civil - Dupla Forma\u00e7\u00e3o\n\nSala:", "horario": [{"dia": "seg", "inicio": "08:10", "fim": "11:50", "professores": ["(R) Jorge Munaiar Neto"]}], "vagas": {"Obrigat\u00f3ria": {"vagas": 50, "inscritos": 40, "pendentes": 0, "matriculados": 0, "grupos": {}}, "Optativa Livre": {"vagas": 5, "inscritos": 0, "pendentes": 0, "matriculados": 0, "grupos": {"EESC - Dupla Forma\u00e7\u00e3o Arquitetura e Urbanismo": {"vagas": 5, "inscritos": 0, "pendentes": 0, "matriculados": 0}, "Qualquer Unidade da USP": {"vagas": 0, "inscritos": 0, "pendentes": 0, "matriculados": 0}}}}}]}