{"unidade": "Faculdade de Zootecnia e Engenharia de Alimentos", "departamento": "Engenharia de Biossistemas", "campus": "Outro", "codigo": "ZEB1045", "nome": "Constru\u00e7\u00f5es Rurais", "creditos_aula": 4, "creditos_trabalho": 0, "objetivos": "Fornecer ao aluno conceitos gerais de materiais e t\u00e9cnicas de constru\u00e7\u00e3o de interesse \u00e0s constru\u00e7\u00f5es rurais, referentes a sistemas construtivos, quantifica\u00e7\u00e3o de materiais e ambi\u00eancia, com aplica\u00e7\u00e3o para instala\u00e7\u00f5es voltadas para a produ\u00e7\u00e3o agropecu\u00e1ria.", "programa_resumido": "Fundamentos de constru\u00e7\u00f5es rurais, materiais de constru\u00e7\u00e3o, no\u00e7\u00f5es de funda\u00e7\u00f5es e estruturas de concreto armado, pr\u00e1tica de pequenas obras, constru\u00e7\u00f5es alternativas, sistemas de cobertura.", "turmas": []}